manifoldy/L2NormCurvature.py
manifoldy/__init__.py
manifoldy/definitions.py
manifoldy/generators.py
manifoldy/reduction_algorithms.py
manifoldy/results.csv
manifoldy/utils.py
manifoldy/test/L2NormCurvature_before_refactor.py
manifoldy/test/__init__.py
manifoldy/test/generators_before_refactor.py
manifoldy/test/refactoring_integration_test.py
manifoldy-0.5.3.dist-info/LICENSE
manifoldy-0.5.3.dist-info/WHEEL
manifoldy-0.5.3.dist-info/METADATA
manifoldy-0.5.3.dist-info/RECORD
