Metadata-Version: 2.1
Name: manifoldy
Version: 0.5.3
Summary: A package to generate customizable manifold synthetic datasets.
Home-page: https://github.com/KNODIS-Research-Group/manifoldy
Author: Raul Lara-Cabrera
Author-email: raul.lara@upm.es
Requires-Python: >=3.8
Classifier: License :: OSI Approved :: GNU General Public License v3 or later (GPLv3+)
Classifier: Intended Audience :: Science/Research
Classifier: Programming Language :: Python :: 3
Classifier: Topic :: Scientific/Engineering :: Artificial Intelligence
Classifier: Topic :: Scientific/Engineering :: Mathematics
Requires-Dist: numpy>=1.18
Requires-Dist: scipy>=1.4
Requires-Dist: ndsplines>=0.1.2
Requires-Dist: joblib>=1.0.1
Requires-Dist: sphinx ; extra == "doc"
Requires-Dist: pytest >=2.7.3 ; extra == "test"
Requires-Dist: pytest-cov ; extra == "test"
Requires-Dist: numpy>=1.18 ; extra == "test"
Requires-Dist: scipy>=1.4 ; extra == "test"
Requires-Dist: ndsplines>=0.1.2 ; extra == "test"
Requires-Dist: joblib>=1.0.1 ; extra == "test"
Provides-Extra: doc
Provides-Extra: test
